starapi/__init__.py
starapi/api.py
starapi/dependency.py
starapi/endpoint.py
starapi/filesystem/__init__.py
starapi/filesystem/driver/__init__.py
starapi/filesystem/driver/gcs.py
starapi/filesystem/driver/interface.py
starapi/filesystem/driver/local.py
starapi/filesystem/service.py
starapi/middleware.py
starapi/spec/__init__.py
starapi/spec/construct.py
starapi/spec/core.py
starapi/types.py
starapi-0.3.3.dist-info/LICENSE
starapi-0.3.3.dist-info/WHEEL
starapi-0.3.3.dist-info/METADATA
starapi-0.3.3.dist-info/RECORD
