Metadata-Version: 2.1
Name: starapi
Version: 0.3.3
Summary: StarAPI based on starlette and pydantic.
Home-page: https://github.com/JonarsLi/flask-restapi
License: MIT
Author: jonars
Author-email: jonarsli13@gmail.com
Requires-Python: >=3.7,<4.0
Classifier: License :: OSI Approved :: MIT License
Classifier: Programming Language :: Python :: 3
Classifier: Programming Language :: Python :: 3.7
Classifier: Programming Language :: Python :: 3.8
Classifier: Programming Language :: Python :: 3.9
Classifier: Programming Language :: Python :: 3.10
Classifier: Programming Language :: Python :: 3.11
Requires-Dist: Jinja2 (>=3.1.2,<4.0.0)
Requires-Dist: google-cloud-storage (>=2.7.0,<3.0.0)
Requires-Dist: pydantic (>=1.10.2,<2.0.0)
Requires-Dist: python-multipart (>=0.0.5,<0.0.6)
Requires-Dist: starlette (>=0.20.4,<0.21.0)
Project-URL: Repository, https://github.com/JonarsLi/flask-restapi
